pyzt/__init__.py
pyzt/pyzt.py
pyzt-1.0.1.dist-info/METADATA
pyzt-1.0.1.dist-info/WHEEL
pyzt-1.0.1.dist-info/top_level.txt
pyzt-1.0.1.dist-info/RECORD
